[
  {
    "name": "Solarion",
    "element": "Plant",
    "monsterId": 1,
    "image": "solarion.gif",
    "shiny": "solarion_shiny.gif",
    "framed": "solarion_framed.gif",
    "sound": "solarion.wav",
    "description": "Self sufficient and able to produce their own light, Solarion often live in solidarity",
    "height": 180,
    "weight": 450,
    "staked": true
  },
  {
    "name": "Bazub",
    "element": "Plant",
    "monsterId": 4,
    "image": "bazub.gif",
    "shiny": "bazub_shiny.gif",
    "framed": "bazub_framed.gif",
    "sound": "bazub.wav",
    "description": "Bazub swarms are deadly and destructive, a swarm can destroy an entire crop in minutes",
    "height": 30,
    "weight": 5,
    "staked": false
  },
  {
    "name": "Bolbon",
    "element": "Plant",
    "monsterId": 5,
    "image": "bolbon.gif",
    "shiny": "bolbon_shiny.gif",
    "framed": "bolbon_framed.gif",
    "sound": "bolbon.wav",
    "description": "Bolbon can sometimes be inactive for so long, that moss, shrubs or even small trees can grow on them",
    "height": 200,
    "weight": 2000,
    "staked": true
  },
  {
    "name": "Antarcticus",
    "element": "Water",
    "monsterId": 17,
    "image": "antarcticus.gif",
    "shiny": "antarcticus_shiny.gif",
    "framed": "antarcticus_framed.gif",
    "sound": "antarcticus.wav",
    "description": "The wings of an Antarcticus emit a cold that can cause saturated clouds to erupt in snow when passed",
    "height": 100,
    "weight": 30,
    "staked": false
  },
  {
    "name": "Woover",
    "element": "Water",
    "monsterId": 18,
    "image": "woover.gif",
    "shiny": "woover_shiny.gif",
    "framed": "woover_framed.gif",
    "sound": "woover.wav",
    "description": "Woovers travel in packs and able to chase down prey over extremely long distances",
    "height": 180,
    "weight": 60,
    "staked": false
  },
  {
    "name": "Lavekans",
    "element": "Fire",
    "monsterId": 19,
    "image": "lavekans.gif",
    "shiny": "lavekans_shiny.gif",
    "framed": "lavekans_framed.gif",
    "sound": "lavekans.wav",
    "description": "Lavekans can be very territorial, and will try to kill any unwelcome intruder by biting it, wrapping around and greatly increasing their body temperature",
    "height": 520,
    "weight": 640,
    "staked": true
  },
  {
    "name": "Calidus",
    "element": "Fire",
    "monsterId": 20,
    "image": "calidus.gif",
    "shiny": "calidus_shiny.gif",
    "framed": "calidus_framed.gif",
    "sound": "calidus.wav",
    "description": "When Calidus sense a threat they can start to burn hot enough to emit waves capable of burning steel from several metres away",
    "height": 250,
    "weight": 4500,
    "staked": true
  },
  {
    "name": "Darthys",
    "element": "Dark",
    "monsterId": 30,
    "image": "darthys.gif",
    "shiny": "darthys_shiny.gif",
    "framed": "darthys_framed.gif",
    "sound": "darthys.wav",
    "description": "If something is killed nearby a Darthys, their soul may be sucked into the crystal on their back and trapped forever",
    "height": 130,
    "weight": 210,
    "staked": false
  },
  {
    "name": "Gryphon",
    "element": "Light",
    "monsterId": 37,
    "image": "gryphon.gif",
    "shiny": "gryphon_shiny.gif",
    "framed": "gryphon_framed.gif",
    "sound": "gryphon.wav",
    "description": "Gryphon can whip their tail to send a shockwave capable cutting through boulders from upto 20 metres away",
    "height": 380,
    "weight": 770,
    "staked": true
  },
  {
    "name": "Pegasus",
    "element": "Light",
    "monsterId": 38,
    "image": "pegasus.gif",
    "shiny": "pegasus_shiny.gif",
    "framed": "pegasus_framed.gif",
    "sound": "pegasus.wav",
    "description": "Pegasus gallop through the sky at such a speed and shine so bright, that they are often mistaken for shooting stars",
    "height": 420,
    "weight": 600,
    "staked": false
  },
  {
    "name": "Templar",
    "element": "Light",
    "monsterId": 39,
    "image": "templar.gif",
    "shiny": "templar_shiny.gif",
    "framed": "templar_framed.gif",
    "sound": "templar.wav",
    "description": "Templar wings are incredibly powerful allowing them to dart through the air and stop or take off immediately",
    "height": 270,
    "weight": 160,
    "staked": false
  }
]